kmapper/__init__.py
kmapper/clustering.py
kmapper/main.py
kmapper/topic_analysis.py
kmapper/visualize.py
doc_mapper-0.0.1.dist-info/LICENSE
doc_mapper-0.0.1.dist-info/METADATA
doc_mapper-0.0.1.dist-info/WHEEL
doc_mapper-0.0.1.dist-info/top_level.txt
doc_mapper-0.0.1.dist-info/RECORD
