Metadata-Version: 2.1
Name: doc-mapper
Version: 0.0.1
Summary: Package to organize and visualize text for a bird's eye view of knowledge
Author: Rintaro-Fukui
License: MIT
License-File: LICENSE
Requires-Dist: gensim ==4.3.2
Requires-Dist: ipython >=8.12.0
Requires-Dist: numpy >=1.26.3
Requires-Dist: scipy >=1.11.4
Requires-Dist: setuptools >=69.0.3
